{
    "questions": [

        {
            "id": "A",
            "question": "zaai ryeth?"
        },
        {
            "id": "B",
            "question": "Waazwaanas manz kya chum touth?"
        },
        {
            "id": "C",
            "question": "Mye pyeth kus rang saarivi khout zyaade shuubaan?"
        },
        {
            "id": "D",
            "question": "Be kya waatyy cxe?"
        },
        {
            "id": "E",
            "question": "Mye manz kus cheez chui cxe pasand?"
        },
        {
            "id": "F",
            "question": "Mye manz kus cheez chui cxe kharaan?"
        },
        {
            "id": "G",
            "question": "Mye kad ryecxx (nickname)."
        },
        {
            "id": "H",
            "question": "Myuon number kami naav seet chi save kormut?"
        },
        {
            "id": "I",
            "question": "Cxe kammi naav seet chuk yecxaan mye bulaavun?"
        },
        {
            "id": "J",
            "question": "Kanh naseeyat myaani baapath?"
        },
        {
            "id": "K",
            "question": "Cxe chuya donkhe logmut ya diutmut kaensi?"
        },
        {
            "id": "L",
            "question": "Mye kas pyeth crush?"
        },
        {
            "id": "M",
            "question": "Saarivi khout boud apuz kya chui wonmut aztaam?"
        },
        {
            "id": "N",
            "question": "Mye cha noon chaai pasand kin na?"
        },
        {
            "id": "O",
            "question": "Be kath cheezas khoucxaan saarivi khout zyaade?"
        },
        {
            "id": "P",
            "question": "Aes kar te kati samkhey goudnik phir?"
        },
        {
            "id": "Q",
            "question": "Kanh raaz yecxaan mye wanun?"
        },
        {
            "id": "R",
            "question": "Cxe kya saarvi khout baed khwaehish?"
        },
        {
            "id": "S",
            "question": "Cxe kath mutliq saarivi khout zyaade kath karaan?"
        },
        {
            "id": "T",
            "question": "Cxe kami cheezuk saarivi khout zyaade gham?"
        }
    ]

}